{"cameraMode":{"drawMode":0,"name":"Shaded","section":"Shading Mode"},"sceneLighting":true,"audioPlay":false,"sceneViewState":{"showFog":true,"showMaterialUpdate":false,"showSkybox":true,"showFlares":true,"showImageEffects":true,"showParticleSystems":true},"in2DMode":false,"pivot":{"x":4327.1005859375,"y":132.6942901611328,"z":1465.3709716796875},"rotation":{"x":-0.19545884430408479,"y":0.02853161096572876,"z":-0.005688886623829603,"w":-0.980280339717865},"size":20.170034408569337,"orthographic":false}